src/pe.v
`default_nettype none
`timescale 1ns / 1ps

// A processing element (PE) module that performs a multiply and accumulate operation.
// A temporal dataflow is used where accumulation occurs over multiple clock cycles.
// We use a weight stationary dataflow where the weight can be stored in the reg file for reuse

module pe #(
    // Parameters for data precision and size of local register file
    parameter IN_PRECISION = 16,
    parameter OUT_PRECISION = 32,      // must be >= IN_PRECISION
    parameter REG_SIZE = 4
) (
    input wire clk,                    // Clock signal
    input wire rst,                    // Reset signal

    input wire [IN_PRECISION-1:0] act, // Input activation
    input wire [IN_PRECISION-1:0] wgt, // Input weight

    input wire store,                  // Store the weight in the reg file
    input wire reuse,                  // Reuse the weight in the reg file
    input wire [REG_SIZE-1:0] addr,    // Address to read/write from reg file
    
    input wire update_out,             // End of current dot product, send output
    output reg [OUT_PRECISION-1:0] out // Output data
);

    // Init local register file. Reserve first reg for temporal accumulation
    reg [OUT_PRECISION-1:0] regfile [REG_SIZE-1:0];

    // Local flag to reset the accumulation in the regfile, not add on
    reg start_new_dot_product; 
    
    // Internal behaviour: multiply act * weight and accumulate into regfile
    always @(posedge clk) begin
        // State A: Resetting
        if (rst) begin
            // Empty the register file
            for (int i=0; i<REG_SIZE; i=i+1) begin
                regfile[i] <= 0;
            end

            // Reset the output
            out <= 0;
            start_new_dot_product <= 0;
        end 
        
        // State B: MAC operation
        else begin
            // Store the weight in the reg file
            if (store) begin
                regfile[addr] <= wgt;
            end 

            // Multiply and accumulate starting from 0 accumulated
            if (start_new_dot_product) begin
                if (reuse) begin                                // with regfile
                    // try a pipelined multiplier here to reduce critical path
                    regfile[0] <= act * regfile[addr];
                end else begin                                  // with new input
                    regfile[0] <= act * wgt;    
                end
                
                start_new_dot_product <= 0;
            end 

            // multiply and accumulate starting with existing accumulation
            else begin
                if (reuse) begin                                    // with regfile
                    regfile[0] <= regfile[0] + act * regfile[addr];
                end else begin                                      // with new input
                    regfile[0] <= regfile[0] + act * wgt;
                end
            end

            // If we are at the end of the dot product, send the output
            if (update_out) begin
                out <= regfile[0];
                start_new_dot_product <= 1; // prep for next dot product next cycle
            end
        end
    end

endmodule

test/pe.vcd
$date
	Fri Sep  6 16:40:04 2024
$end
$version
	Icarus Verilog
$end
$timescale
	1ps
$end
$scope module pe $end
$var wire 16 ! act [15:0] $end
$var wire 4 " addr [3:0] $end
$var wire 1 # clk $end
$var wire 1 $ reuse $end
$var wire 1 % rst $end
$var wire 1 & store $end
$var wire 1 ' update_out $end
$var wire 16 ( wgt [15:0] $end
$var parameter 32 ) IN_PRECISION $end
$var parameter 32 * OUT_PRECISION $end
$var parameter 32 + REG_SIZE $end
$var reg 32 , out [31:0] $end
$var reg 1 - start_new_dot_product $end
$scope begin $ivl_for_loop0 $end
$var integer 32 . i [31:0] $end
$upscope $end
$upscope $end
$scope module pe $end
$var reg 32 / \regfile[0] [31:0] $end
$upscope $end
$scope module pe $end
$var reg 32 0 \regfile[1] [31:0] $end
$upscope $end
$scope module pe $end
$var reg 32 1 \regfile[2] [31:0] $end
$upscope $end
$scope module pe $end
$var reg 32 2 \regfile[3] [31:0] $end
$upscope $end
$enddefinitions $end
$comment Show the parameter values. $end
$dumpall
b100 +
b100000 *
b10000 )
$end
#0
$dumpvars
b0 2
b0 1
b0 0
b0 /
b100 .
0-
b0 ,
b0 (
0'
0&
1%
0$
1#
b0 "
b0 !
$end
#5000000
0#
#10000000
b0 2
b0 1
b0 0
b0 /
b100 .
1#
#15000000
0#
#20000000
b0 2
b0 1
b0 0
b0 /
b100 .
1#
#25000000
0#
#30000000
b0 2
b0 1
b0 0
b0 /
b100 .
1#
#35000000
0#
#40000000
0%
b0 2
b0 1
b0 0
b0 /
b100 .
1#
#45000000
0#
#50000000
b0 /
1#
#55000000
0#
#60000000
b0 /
1#
#65000000
0#
#70000000
b0 /
1#
#75000000
0#
#80000000
b0 /
1#
#85000000
0#
#90000000
1%
b0 /
1#
#95000000
0#
#100000000
b0 2
b0 1
b0 0
b0 /
b100 .
1#
#105000000
0#
#110000000
b0 2
b0 1
b0 0
b0 /
b100 .
1#
#115000000
0#
#120000000
b0 2
b0 1
b0 0
b0 /
b100 .
1#
#125000000
0#
#130000000
b0 2
b0 1
b0 0
b0 /
b100 .
1#
#135000000
0#
#140000000
0%
b0 2
b0 1
b0 0
b0 /
b100 .
1#
#145000000
0#
#150000000
b0 /
1#
#155000000
0#
#160000000
b0 /
1#
#165000000
0#
#170000000
b0 /
1#
#175000000
0#
#180000000
b0 /
1#
#185000000
0#
#190000000
b0 /
1#
#190000001
1%
#195000001
0#
#200000001
b0 2
b0 1
b0 0
b0 /
b100 .
1#
#205000001
0#
#210000001
b0 2
b0 1
b0 0
b0 /
b100 .
1#
#215000001
0#
#220000001
b0 2
b0 1
b0 0
b0 /
b100 .
1#
#225000001
0#
#230000001
b0 2
b0 1
b0 0
b0 /
b100 .
1#
#235000001
0#
#240000001
0%
b0 2
b0 1
b0 0
b0 /
b100 .
1#
#245000001
0#
#250000001
b0 /
1#
#255000001
0#
#260000001
b0 /
1#
#265000001
0#
#270000001
b0 /
1#
#275000001
0#
#280000001
b0 /
1#
#285000001
0#
#290000001
1'
b1100 (
b111001 !
b0 /
1#
#295000001
0#
#300000001
1-
b1010101100 /
1#
#305000001
0#
#310000001
b1010101100 ,
1-
b1010101100 /
1#
#315000001
0#
#320000001
b1111101 (
b10001100 !
1-
b1010101100 /
1#
#325000001
0#
#330000001
1-
b100010001011100 /
1#
#335000001
0#
#340000001
b100010001011100 ,
1-
b100010001011100 /
1#
#345000001
0#
#350000001
b1000111 (
b1110010 !
1-
b100010001011100 /
1#
#355000001
0#
#360000001
1-
b1111110011110 /
1#
#365000001
0#
#370000001
b1111110011110 ,
1-
b1111110011110 /
1#
#375000001
0#
#380000001
b101100 (
b110100 !
1-
b1111110011110 /
1#
#385000001
0#
#390000001
1-
b100011110000 /
1#
#395000001
0#
#400000001
b100011110000 ,
1-
b100011110000 /
1#
#405000001
0#
#410000001
b10000 (
b11011000 !
1-
b100011110000 /
1#
#415000001
0#
#420000001
1-
b110110000000 /
1#
#425000001
0#
#430000001
b110110000000 ,
1-
b110110000000 /
1#
#435000001
0#
#440000001
b101111 (
b1111 !
1-
b110110000000 /
1#
#445000001
0#
#450000001
1-
b1011000001 /
1#
#455000001
0#
#460000001
b1011000001 ,
1-
b1011000001 /
1#
#465000001
0#
#470000001
b1110111 (
b1101111 !
1-
b1011000001 /
1#
#475000001
0#
#480000001
1-
b11001110011001 /
1#
#485000001
0#
#490000001
b11001110011001 ,
1-
b11001110011001 /
1#
#495000001
0#
#500000001
b1100101 (
b1101 !
1-
b11001110011001 /
1#
#505000001
0#
#510000001
1-
b10100100001 /
1#
#515000001
0#
#520000001
b10100100001 ,
1-
b10100100001 /
1#
#525000001
0#
#530000001
b1110000 (
b11010110 !
1-
b10100100001 /
1#
#535000001
0#
#540000001
1-
b101110110100000 /
1#
#545000001
0#
#550000001
b101110110100000 ,
1-
b101110110100000 /
1#
#555000001
0#
#560000001
b10001110 (
b11100101 !
1-
b101110110100000 /
1#
#565000001
0#
#570000001
1-
b111111100000110 /
1#
#575000001
0#
#580000001
b111111100000110 ,
1-
b111111100000110 /
1#
#585000001
0#
#590000001
1%
0'
b0 (
b0 !
1-
b111111100000110 /
1#
#595000001
0#
#600000001
0-
b0 ,
b0 2
b0 1
b0 0
b0 /
b100 .
1#
#605000001
0#
#610000001
b0 2
b0 1
b0 0
b0 /
b100 .
1#
#615000001
0#
#620000001
b0 2
b0 1
b0 0
b0 /
b100 .
1#
#625000001
0#
#630000001
b0 2
b0 1
b0 0
b0 /
b100 .
1#
#635000001
0#
#640000001
0%
b0 2
b0 1
b0 0
b0 /
b100 .
1#
#645000001
0#
#650000001
b0 /
1#
#655000001
0#
#660000001
b0 /
1#
#665000001
0#
#670000001
b0 /
1#
#675000001
0#
#680000001
b0 /
1#
#685000001
0#
#690000001
b0 /
1#
#690000002
1%
#695000002
0#
#700000002
b0 2
b0 1
b0 0
b0 /
b100 .
1#
#705000002
0#
#710000002
b0 2
b0 1
b0 0
b0 /
b100 .
1#
#715000002
0#
#720000002
b0 2
b0 1
b0 0
b0 /
b100 .
1#
#725000002
0#
#730000002
b0 2
b0 1
b0 0
b0 /
b100 .
1#
#735000002
0#
#740000002
0%
b0 2
b0 1
b0 0
b0 /
b100 .
1#
#745000002
0#
#750000002
b0 /
1#
#755000002
0#
#760000002
b0 /
1#
#765000002
0#
#770000002
b0 /
1#
#775000002
0#
#780000002
b0 /
1#
#785000002
0#
#790000002
b1100 (
b111001 !
b0 /
1#
#795000002
0#
#800000002
b1010101100 /
1#
#805000002
0#
#810000002
b10101011000 /
1#
#815000002
0#
#820000002
b100000000100 /
1#
#820000003
1%
b0 (
b0 !
#825000003
0#
#830000003
b0 2
b0 1
b0 0
b0 /
b100 .
1#
#835000003
0#
#840000003
b0 2
b0 1
b0 0
b0 /
b100 .
1#
#845000003
0#
#850000003
b0 2
b0 1
b0 0
b0 /
b100 .
1#
#855000003
0#
#860000003
b0 2
b0 1
b0 0
b0 /
b100 .
1#
#865000003
0#
#870000003
0%
b0 2
b0 1
b0 0
b0 /
b100 .
1#
#875000003
0#
#880000003
b0 /
1#
#885000003
0#
#890000003
b0 /
1#
#895000003
0#
#900000003
b0 /
1#
#905000003
0#
#910000003
b0 /
1#
#915000003
0#
#920000003
b1 "
1&
b1100 (
b111001 !
b0 /
1#
#925000003
0#
#930000003
b1010101100 /
b1100 0
1#
