src/pe.v
`default_nettype none
`timescale 1ns / 1ps

// A processing element (PE) module that performs a multiply and accumulate operation.
// A temporal dataflow is used where accumulation occurs over multiple clock cycles.
// We use a weight stationary dataflow where the weight can be stored in the reg file for reuse

module pe #(
    // Parameters for data precision and size of local register file
    parameter IN_PRECISION = 16,
    parameter OUT_PRECISION = 32,      // must be >= IN_PRECISION
    parameter REG_SIZE = 4
) (
    input wire clk,                    // Clock signal
    input wire rst,                    // Reset signal

    input wire [IN_PRECISION-1:0] act, // Input activation
    input wire [IN_PRECISION-1:0] wgt, // Input weight

    input wire store,                  // Store the weight in the reg file
    input wire reuse,                  // Reuse the weight in the reg file
    input wire [REG_SIZE-1:0] addr,    // Address to read/write from reg file
    
    input wire finish,                 // End of current dot product, send output
    output reg [OUT_PRECISION-1:0] out // Output data
);

    // Init local register file. Reserve first reg for temporal accumulation
    reg [OUT_PRECISION-1:0] regfile [REG_SIZE-1:0];
    
    // Internal behaviour: multiply act * weight and accumulate into regfile
    always @(posedge clk) begin
        if (rst) begin
            // Empty the register file
            for (int i=0; i<REG_SIZE; i=i+1) begin
                regfile[i] <= 0;
            end

            // Reset the output
            out <= 0;
        end else begin
            // Store the weight in the reg file
            if (store) begin
                regfile[addr] <= wgt;
            end 

            // Multiply and accumulate 
            if (reuse) begin                                    // with regfile
                regfile[0] <= regfile[0] + act * regfile[addr];
            end else begin                                      // with new input
                regfile[0] <= regfile[0] + act * wgt;
            end

            // If we are at the end of the dot product, send the output
            if (finish) begin
                out <= regfile[0];
                //regfile[0] <= 0; // prep for next dot product
            end
        end
    end

endmodule

test/pe.vcd
$date
	Fri Sep  6 16:20:31 2024
$end
$version
	Icarus Verilog
$end
$timescale
	1ps
$end
$scope module pe $end
$var wire 16 ! act [15:0] $end
$var wire 4 " addr [3:0] $end
$var wire 1 # clk $end
$var wire 1 $ finish $end
$var wire 1 % reuse $end
$var wire 1 & rst $end
$var wire 1 ' store $end
$var wire 16 ( wgt [15:0] $end
$var parameter 32 ) IN_PRECISION $end
$var parameter 32 * OUT_PRECISION $end
$var parameter 32 + REG_SIZE $end
$var reg 32 , out [31:0] $end
$scope begin $ivl_for_loop0 $end
$var integer 32 - i [31:0] $end
$upscope $end
$upscope $end
$scope module pe $end
$var reg 32 . \regfile[0] [31:0] $end
$upscope $end
$scope module pe $end
$var reg 32 / \regfile[1] [31:0] $end
$upscope $end
$scope module pe $end
$var reg 32 0 \regfile[2] [31:0] $end
$upscope $end
$scope module pe $end
$var reg 32 1 \regfile[3] [31:0] $end
$upscope $end
$enddefinitions $end
$comment Show the parameter values. $end
$dumpall
b100 +
b100000 *
b10000 )
$end
#0
$dumpvars
b0 1
b0 0
b0 /
b0 .
b100 -
b0 ,
b0 (
0'
1&
0%
0$
1#
b0 "
b0 !
$end
#5000000
0#
#10000000
b0 1
b0 0
b0 /
b0 .
b100 -
1#
#15000000
0#
#20000000
b0 1
b0 0
b0 /
b0 .
b100 -
1#
#25000000
0#
#30000000
b0 1
b0 0
b0 /
b0 .
b100 -
1#
#35000000
0#
#40000000
0&
b0 1
b0 0
b0 /
b0 .
b100 -
1#
#45000000
0#
#50000000
b0 .
1#
#55000000
0#
#60000000
b0 .
1#
#65000000
0#
#70000000
b0 .
1#
#75000000
0#
#80000000
b0 .
1#
#85000000
0#
#90000000
1&
b0 .
1#
#95000000
0#
#100000000
b0 1
b0 0
b0 /
b0 .
b100 -
1#
#105000000
0#
#110000000
b0 1
b0 0
b0 /
b0 .
b100 -
1#
#115000000
0#
#120000000
b0 1
b0 0
b0 /
b0 .
b100 -
1#
#125000000
0#
#130000000
b0 1
b0 0
b0 /
b0 .
b100 -
1#
#135000000
0#
#140000000
0&
b0 1
b0 0
b0 /
b0 .
b100 -
1#
#145000000
0#
#150000000
b0 .
1#
#155000000
0#
#160000000
b0 .
1#
#165000000
0#
#170000000
b0 .
1#
#175000000
0#
#180000000
b0 .
1#
#185000000
0#
#190000000
b0 .
1#
#190000001
1&
#195000001
0#
#200000001
b0 1
b0 0
b0 /
b0 .
b100 -
1#
#205000001
0#
#210000001
b0 1
b0 0
b0 /
b0 .
b100 -
1#
#215000001
0#
#220000001
b0 1
b0 0
b0 /
b0 .
b100 -
1#
#225000001
0#
#230000001
b0 1
b0 0
b0 /
b0 .
b100 -
1#
#235000001
0#
#240000001
0&
b0 1
b0 0
b0 /
b0 .
b100 -
1#
#245000001
0#
#250000001
b0 .
1#
#255000001
0#
#260000001
b0 .
1#
#265000001
0#
#270000001
b0 .
1#
#275000001
0#
#280000001
b0 .
1#
#285000001
0#
#290000001
1$
b1100 (
b111001 !
b0 .
1#
#295000001
0#
#300000001
b0 .
1#
#305000001
0#
#310000001
b0 .
1#
#315000001
0#
#320000001
b0 .
1#
#320000002
1&
0$
b0 (
b0 !
#325000002
0#
#330000002
b0 1
b0 0
b0 /
b0 .
b100 -
1#
#335000002
0#
#340000002
b0 1
b0 0
b0 /
b0 .
b100 -
1#
#345000002
0#
#350000002
b0 1
b0 0
b0 /
b0 .
b100 -
1#
#355000002
0#
#360000002
b0 1
b0 0
b0 /
b0 .
b100 -
1#
#365000002
0#
#370000002
0&
b0 1
b0 0
b0 /
b0 .
b100 -
1#
#375000002
0#
#380000002
b0 .
1#
#385000002
0#
#390000002
b0 .
1#
#395000002
0#
#400000002
b0 .
1#
#405000002
0#
#410000002
b0 .
1#
#415000002
0#
#420000002
b1100 (
b111001 !
b0 .
1#
#425000002
0#
#430000002
b1010101100 .
1#
#435000002
0#
#440000002
b10101011000 .
1#
#445000002
0#
#450000002
b100000000100 .
1#
#450000003
1&
b0 (
b0 !
#455000003
0#
#460000003
b0 1
b0 0
b0 /
b0 .
b100 -
1#
#465000003
0#
#470000003
b0 1
b0 0
b0 /
b0 .
b100 -
1#
#475000003
0#
#480000003
b0 1
b0 0
b0 /
b0 .
b100 -
1#
#485000003
0#
#490000003
b0 1
b0 0
b0 /
b0 .
b100 -
1#
#495000003
0#
#500000003
0&
b0 1
b0 0
b0 /
b0 .
b100 -
1#
#505000003
0#
#510000003
b0 .
1#
#515000003
0#
#520000003
b0 .
1#
#525000003
0#
#530000003
b0 .
1#
#535000003
0#
#540000003
b0 .
1#
#545000003
0#
#550000003
b1 "
1'
b1100 (
b111001 !
b0 .
1#
#555000003
0#
#560000003
b1010101100 .
b1100 /
1#
