src/pe.v
`default_nettype none
`timescale 1ns / 1ps

// A processing element (PE) module that performs a multiply and accumulate operation.
// A temporal dataflow is used where accumulation occurs over multiple clock cycles.
// We use a weight stationary dataflow where the weight can be stored in the reg file for reuse

module pe #(
    // Parameters for data precision and size of local register file
    parameter IN_PRECISION = 16,
    parameter OUT_PRECISION = 32,      // must be >= IN_PRECISION
    parameter REG_SIZE = 4
) (
    input wire clk,                    // Clock signal
    input wire rst,                    // Reset signal

    input wire [IN_PRECISION-1:0] act, // Input activation
    input wire [IN_PRECISION-1:0] wgt, // Input weight

    input wire store,                  // Store the weight in the reg file
    input wire reuse,                  // Reuse the weight in the reg file
    input wire [REG_SIZE-1:0] addr,    // Address to read/write from reg file
    
    input wire finish,                 // End of current dot product, send output
    output reg [OUT_PRECISION-1:0] out // Output data
);

    // Init local register file. Reserve first reg for temporal accumulation
    reg [OUT_PRECISION-1:0] regfile [REG_SIZE-1:0];
    
    // Internal behaviour: multiply act * weight and accumulate into regfile
    always @(posedge clk) begin
        if (rst) begin
            // Empty the register file
            for (int i=0; i<REG_SIZE; i=i+1) begin
                regfile[i] <= 0;
            end

            // Reset the output
            out <= 0;
        end else begin
            // Store the weight in the reg file
            if (store) begin
                regfile[addr] <= wgt;
            end 

            // Multiply and accumulate 
            if (reuse) begin                                    // with regfile
                regfile[0] <= regfile[0] + act * regfile[addr];
            end else begin                                      // with new input
                regfile[0] <= regfile[0] + act * wgt;
            end

            // If we are at the end of the dot product, send the output
            if (finish) begin
                out <= regfile[0];
                //? If I include this, the output is 0. Why?
                regfile[0] <= 0; // prep for next dot product
            end
        end
    end

endmodule

test/pe.vcd
$date
	Tue Sep  3 16:52:14 2024
$end
$version
	Icarus Verilog
$end
$timescale
	1ps
$end
$scope module pe $end
$var wire 16 ! act [15:0] $end
$var wire 4 " addr [3:0] $end
$var wire 1 # clk $end
$var wire 1 $ finish $end
$var wire 1 % reuse $end
$var wire 1 & rst $end
$var wire 1 ' store $end
$var wire 16 ( wgt [15:0] $end
$var parameter 32 ) IN_PRECISION $end
$var parameter 32 * OUT_PRECISION $end
$var parameter 32 + REG_SIZE $end
$var reg 32 , out [31:0] $end
$scope begin $ivl_for_loop0 $end
$var integer 32 - i [31:0] $end
$upscope $end
$upscope $end
$enddefinitions $end
$comment Show the parameter values. $end
$dumpall
b100 +
b100000 *
b10000 )
$end
#0
$dumpvars
b100 -
b0 ,
b0 (
0'
1&
0%
0$
1#
b0 "
b0 !
$end
#5000000
0#
#10000000
b100 -
1#
#15000000
0#
#20000000
b100 -
1#
#25000000
0#
#30000000
b100 -
1#
#35000000
0#
#40000000
0&
b100 -
1#
#45000000
0#
#50000000
1#
#55000000
0#
#60000000
1#
#65000000
0#
#70000000
1#
#75000000
0#
#80000000
1#
#85000000
0#
#90000000
1&
1#
#95000000
0#
#100000000
b100 -
1#
#105000000
0#
#110000000
b100 -
1#
#115000000
0#
#120000000
b100 -
1#
#125000000
0#
#130000000
b100 -
1#
#135000000
0#
#140000000
0&
b100 -
1#
#145000000
0#
#150000000
1#
#155000000
0#
#160000000
1#
#165000000
0#
#170000000
1#
#175000000
0#
#180000000
1#
#185000000
0#
#190000000
1#
#190000001
1&
#195000001
0#
#200000001
b100 -
1#
#205000001
0#
#210000001
b100 -
1#
#215000001
0#
#220000001
b100 -
1#
#225000001
0#
#230000001
b100 -
1#
#235000001
0#
#240000001
0&
b100 -
1#
#245000001
0#
#250000001
1#
#255000001
0#
#260000001
1#
#265000001
0#
#270000001
1#
#275000001
0#
#280000001
1#
#285000001
0#
#290000001
1$
b10010001 (
b10010001 !
1#
#295000001
0#
#300000001
1#
#305000001
0#
#310000001
b101001000100001 ,
1#
#315000001
0#
#320000001
1&
0$
b0 (
b0 !
b1010010001000010 ,
1#
#325000001
0#
#330000001
b0 ,
b100 -
1#
#335000001
0#
#340000001
b100 -
1#
#345000001
0#
#350000001
b100 -
1#
#355000001
0#
#360000001
b100 -
1#
#365000001
0#
#370000001
0&
b100 -
1#
#375000001
0#
#380000001
1#
#385000001
0#
#390000001
1#
#395000001
0#
#400000001
1#
#405000001
0#
#410000001
1#
#415000001
0#
#420000001
1#
#420000002
1&
#425000002
0#
#430000002
b100 -
1#
#435000002
0#
#440000002
b100 -
1#
#445000002
0#
#450000002
b100 -
1#
#455000002
0#
#460000002
b100 -
1#
#465000002
0#
#470000002
0&
b100 -
1#
#475000002
0#
#480000002
1#
#485000002
0#
#490000002
1#
#495000002
0#
#500000002
1#
#505000002
0#
#510000002
1#
#515000002
0#
#520000002
b11101001 (
b10110110 !
1#
#525000002
0#
#530000002
b11010000 (
b11111101 !
1#
#535000002
0#
#540000002
b101110 (
b10000110 !
1#
#545000002
0#
#550000002
b11101100 (
b11001011 !
1#
#555000002
0#
#560000002
b10011101 (
b111111 !
1#
#565000002
0#
#570000002
b1000010 (
b10010101 !
1#
#575000002
0#
#580000002
b11011001 (
b1101 !
1#
#585000002
0#
#590000002
b11011 (
b11101010 !
1#
#595000002
0#
#600000002
b1110 (
b101000 !
1#
#605000002
0#
#610000002
b11000011 (
b1011011 !
1#
#615000002
0#
#620000002
1$
b10010000 (
b1101010 !
1#
#625000002
0#
#630000002
b101111111010101111 ,
1#
#630000003
1&
0$
b0 (
b0 !
#635000003
0#
#640000003
b0 ,
b100 -
1#
#645000003
0#
#650000003
b100 -
1#
#655000003
0#
#660000003
b100 -
1#
#665000003
0#
#670000003
b100 -
1#
#675000003
0#
#680000003
0&
b100 -
1#
#685000003
0#
#690000003
1#
#695000003
0#
#700000003
1#
#705000003
0#
#710000003
1#
#715000003
0#
#720000003
1#
#725000003
0#
#730000003
b1 "
1'
b11010101 (
b1110001 !
1#
